shardmonster/sharder.py
shardmonster/metadata.py
shardmonster/operations.py
shardmonster/api.py
shardmonster/__init__.py
shardmonster/connection.py
shardmonster/tests/test_operations.py
shardmonster/tests/test_api.py
shardmonster/tests/test_connection.py
shardmonster/tests/test_integration.py
shardmonster/tests/base.py
shardmonster/tests/__init__.py
shardmonster/tests/test_metadata.py
shardmonster/tests/test_sharder.py
shardmonster-0.7.1.dist-info/METADATA
shardmonster-0.7.1.dist-info/metadata.json
shardmonster-0.7.1.dist-info/WHEEL
shardmonster-0.7.1.dist-info/DESCRIPTION.rst
shardmonster-0.7.1.dist-info/top_level.txt
shardmonster-0.7.1.dist-info/RECORD
